pathology_foundation_models/__init__.py
pathology_foundation_models/dataset/__init__.py
pathology_foundation_models/dataset/cached_embedding.py
pathology_foundation_models/models/__init__.py
pathology_foundation_models/models/config.py
pathology_foundation_models/models/fm_model.py
pathology_foundation_models/models/inference.py
pathology_foundation_models/models/adapters/__init__.py
pathology_foundation_models/models/adapters/inference.py
pathology_foundation_models/models/adapters/loader.py
pathology_foundation_models/tests/__init__.py
pathology_foundation_models/tests/fixtures.py
pathology_foundation_models/tests/test_embedding_cache.py
pathology_foundation_models/tests/test_inference.py
pathology_foundation_models/tests/test_loader.py
pathology_foundation_models-0.0.3.dist-info/LICENSE
pathology_foundation_models-0.0.3.dist-info/METADATA
pathology_foundation_models-0.0.3.dist-info/WHEEL
pathology_foundation_models-0.0.3.dist-info/top_level.txt
pathology_foundation_models-0.0.3.dist-info/RECORD
